djace_editor/__init__.py
djace_editor/fields.py
djace_editor/widgets.py
djace_editor/static/djace_editor/widget.css
djace_editor/static/djace_editor/widget.js
djace_editor/static/djace_editor/ace/.DS_Store
djace_editor/static/djace_editor/ace/ace.js
djace_editor/static/djace_editor/ace/ext-beautify.js
djace_editor/static/djace_editor/ace/ext-elastic_tabstops_lite.js
djace_editor/static/djace_editor/ace/ext-emmet.js
djace_editor/static/djace_editor/ace/ext-error_marker.js
djace_editor/static/djace_editor/ace/ext-keybinding_menu.js
djace_editor/static/djace_editor/ace/ext-language_tools.js
djace_editor/static/djace_editor/ace/ext-linking.js
djace_editor/static/djace_editor/ace/ext-modelist.js
djace_editor/static/djace_editor/ace/ext-options.js
djace_editor/static/djace_editor/ace/ext-rtl.js
djace_editor/static/djace_editor/ace/ext-searchbox.js
djace_editor/static/djace_editor/ace/ext-settings_menu.js
djace_editor/static/djace_editor/ace/ext-spellcheck.js
djace_editor/static/djace_editor/ace/ext-split.js
djace_editor/static/djace_editor/ace/ext-static_highlight.js
djace_editor/static/djace_editor/ace/ext-statusbar.js
djace_editor/static/djace_editor/ace/ext-textarea.js
djace_editor/static/djace_editor/ace/ext-themelist.js
djace_editor/static/djace_editor/ace/ext-whitespace.js
djace_editor/static/djace_editor/ace/keybinding-emacs.js
djace_editor/static/djace_editor/ace/keybinding-vim.js
djace_editor/static/djace_editor/ace/mode-abap.js
djace_editor/static/djace_editor/ace/mode-abc.js
djace_editor/static/djace_editor/ace/mode-actionscript.js
djace_editor/static/djace_editor/ace/mode-ada.js
djace_editor/static/djace_editor/ace/mode-apache_conf.js
djace_editor/static/djace_editor/ace/mode-apex.js
djace_editor/static/djace_editor/ace/mode-applescript.js
djace_editor/static/djace_editor/ace/mode-asciidoc.js
djace_editor/static/djace_editor/ace/mode-asl.js
djace_editor/static/djace_editor/ace/mode-assembly_x86.js
djace_editor/static/djace_editor/ace/mode-autohotkey.js
djace_editor-1.0.0.dist-info/LICENCE
djace_editor-1.0.0.dist-info/METADATA
djace_editor-1.0.0.dist-info/WHEEL
djace_editor-1.0.0.dist-info/top_level.txt
djace_editor-1.0.0.dist-info/RECORD
