Metadata-Version: 2.1
Name: djace-editor
Version: 1.0.0
Summary: djace_editor provides integration for ajax.org ACE with Django
Home-page: https://github.com/smidth/django-ace-editor
Author: Alex Vakhitov
Author-email: alex.vakhitov@gmail.com
License: Simplified BSD
Platform: UNKNOWN
Classifier: Development Status :: 4 - Beta
Classifier: Environment :: Web Environment
Classifier: Intended Audience :: Developers
Classifier: License :: OSI Approved :: BSD License
Classifier: Operating System :: OS Independent
Classifier: Programming Language :: Python
Classifier: Framework :: Django
Requires-Dist: django (>=1.9)
Requires-Dist: setuptools
